verilog/fifo_mux_16_1.sv
module fifo_mux_16_1 #(
    parameter int BW   = 4,
    parameter int SIMD = 8
) (
    input  logic [        3:0] sel,
    input  logic [SIMD*BW-1:0] in [16],
    output logic [SIMD*BW-1:0] out
);

  always_comb out = in[sel];

endmodule

verilog/fifo_depth16.sv
module fifo_depth16 #(
    parameter int BW   = 4,
    parameter int SIMD = 1
) (
    input  logic               rd_clk,
    input  logic               wr_clk,
    input  logic               rd,
    input  logic               wr,
    input  logic               reset,
    input  logic [SIMD*BW-1:0] in,
    output logic [SIMD*BW-1:0] out,
    output logic               o_full,
    output logic               o_empty
);

  logic full, empty;

  logic [4:0] rd_ptr = 5'b00000;
  logic [4:0] wr_ptr = 5'b00000;

  logic [SIMD*BW-1:0] q[16];

  always_comb begin
    empty = (wr_ptr == rd_ptr) ? 1'b1 : 1'b0;
    full = ((wr_ptr[3:0] == rd_ptr[3:0]) && (wr_ptr[4] != rd_ptr[4])) ? 1'b1 : 1'b0;
    o_full = full;
    o_empty = empty;
  end

  fifo_mux_16_1 #(
      .BW  (BW),
      .SIMD(SIMD)
  ) fifo_mux_16_1a (
      .in (q),
      .sel(rd_ptr[3:0]),
      .out(out)
  );

  always_ff @(posedge rd_clk) begin
    if (reset) rd_ptr <= 5'b00000;
    else if ((rd == 1) && (empty == 0)) rd_ptr <= rd_ptr + 1;
  end

  always_ff @(posedge wr_clk) begin
    if (reset) wr_ptr <= 5'b00000;
    else begin
      if ((wr == 1) && (full == 0)) wr_ptr <= wr_ptr + 1;

      if (wr == 1) q[wr_ptr[3:0]] <= in;
    end
  end

endmodule

verilog/mac_16in.sv
module mac_16in #(
    parameter int BW      = 8,
    parameter int BW_PSUM = 2 * BW + 6,
    parameter int PR      = 64
) (
    input  logic [  PR*BW-1:0] a,
    input  logic [  PR*BW-1:0] b,
    output logic [BW_PSUM-1:0] out
);

  logic [2*BW-1:0] product[16];

  always_comb begin
    for (int i = 0; i < 16; i++) begin
      product[i] = {{(BW){a[BW*(i+1)-1]}}, a[BW*(i+1)-1 -: BW]}
                  * {{(BW){b[BW*(i+1)-1]}}, b[BW*(i+1)-1 -: BW]};
    end

    out = '0;
    for (int i = 0; i < 16; i++) out = out + {{(4) {product[i][2*BW-1]}}, product[i]};
  end

endmodule

verilog/sram_128b_w16.sv
module sram_128b_w16 (
    input  logic         CLK,
    input  logic         WEN,
    input  logic         CEN,
    input  logic [127:0] D,
    input  logic [  3:0] A,
    output logic [127:0] Q
);

  logic [127:0] memory[16];
  logic [  3:0] add_q;

  always_comb Q = memory[add_q];

  always_ff @(posedge CLK) begin
    if (!CEN && WEN)  // read
      add_q <= A;
    if (!CEN && !WEN)  // write
      memory[A] <= D;
  end

endmodule

verilog/sram_w16.sv
module sram_w16 #(
    parameter int SRAM_BIT = 128
) (
    input  logic                CLK,
    input  logic                WEN,
    input  logic                CEN,
    input  logic [SRAM_BIT-1:0] D,
    input  logic [         3:0] A,
    output logic [SRAM_BIT-1:0] Q
);

  logic [SRAM_BIT-1:0] memory[16];

  always_ff @(posedge CLK) begin
    if (!CEN && WEN)  // read
      Q <= memory[A];
    else if (!CEN && !WEN)  // write
      memory[A] <= D;
  end

endmodule

verilog/refactor_tb.sv
`timescale 1ns / 1ps

// Testbench to verify refactored modules (packed -> unpacked array conversion)
module refactor_tb;

  parameter int BW = 8;
  parameter int BW_PSUM = 2 * BW + 4;
  parameter int PR = 16;
  parameter int SRAM_BIT = 128;

  integer pass_count, fail_count;
  integer i, j;

  //=========================================================
  // Clock generation
  //=========================================================
  logic clk = 0;
  always #0.5 clk = ~clk;

  //=========================================================
  // 1. Test sram_w16 (memory[16] array)
  //=========================================================
  logic sram_wen, sram_cen;
  logic [SRAM_BIT-1:0] sram_d, sram_q;
  logic [3:0] sram_a;

  sram_w16 #(
      .SRAM_BIT(SRAM_BIT)
  ) uut_sram (
      .CLK(clk),
      .WEN(sram_wen),
      .CEN(sram_cen),
      .D  (sram_d),
      .A  (sram_a),
      .Q  (sram_q)
  );

  //=========================================================
  // 2. Test sram_128b_w16 (memory[16] array, async read)
  //=========================================================
  logic sram128_wen, sram128_cen;
  logic [127:0] sram128_d, sram128_q;
  logic [3:0] sram128_a;

  sram_128b_w16 uut_sram128 (
      .CLK(clk),
      .WEN(sram128_wen),
      .CEN(sram128_cen),
      .D  (sram128_d),
      .A  (sram128_a),
      .Q  (sram128_q)
  );

  //=========================================================
  // 3. Test mac_16in (product[16] array)
  //=========================================================
  logic [PR*BW-1:0] mac_a, mac_b;
  logic [BW_PSUM-1:0] mac_out;

  mac_16in #(
      .BW(BW),
      .BW_PSUM(BW_PSUM),
      .PR(PR)
  ) uut_mac16 (
      .a  (mac_a),
      .b  (mac_b),
      .out(mac_out)
  );

  //=========================================================
  // 4. Test fifo_depth16 (q[16] array)
  //=========================================================
  logic fifo_rd, fifo_wr, fifo_reset;
  logic [BW-1:0] fifo_in, fifo_out;
  logic fifo_full, fifo_empty;

  fifo_depth16 #(
      .BW  (BW),
      .SIMD(1)
  ) uut_fifo (
      .rd_clk(clk),
      .wr_clk(clk),
      .rd(fifo_rd),
      .wr(fifo_wr),
      .reset(fifo_reset),
      .in(fifo_in),
      .out(fifo_out),
      .o_full(fifo_full),
      .o_empty(fifo_empty)
  );

  //=========================================================
  // Test sequence
  //=========================================================
  initial begin
    $dumpfile("refactor_tb.vcd");
    $dumpvars(0, refactor_tb);

    pass_count = 0;
    fail_count = 0;

    // Initialize
    sram_wen = 1;
    sram_cen = 1;
    sram_d = 0;
    sram_a = 0;
    sram128_wen = 1;
    sram128_cen = 1;
    sram128_d = 0;
    sram128_a = 0;
    mac_a = 0;
    mac_b = 0;
    fifo_rd = 0;
    fifo_wr = 0;
    fifo_reset = 1;
    fifo_in = 0;

    // Wait for reset
    repeat (3) @(posedge clk);

    //-------------------------------------------------------
    // Test 1: sram_w16 - write all 16 addresses, read back
    //-------------------------------------------------------
    $display("\n===== Test 1: sram_w16 =====");

    // Write phase
    for (i = 0; i < 16; i++) begin
      @(negedge clk);
      sram_cen = 0;
      sram_wen = 0;  // write
      sram_a   = i[3:0];
      sram_d   = (i + 1) * 128'hDEAD_0001;  // unique pattern per address
      @(posedge clk);
    end

    @(negedge clk);
    sram_cen = 1;
    sram_wen = 1;
    @(posedge clk);

    // Read phase
    for (i = 0; i < 16; i++) begin
      @(negedge clk);
      sram_cen = 0;
      sram_wen = 1;  // read
      sram_a   = i[3:0];
      @(posedge clk);
      // Q is registered, available next cycle
      @(negedge clk);
      sram_cen = 1;
      @(posedge clk);
      if (sram_q == (i + 1) * 128'hDEAD_0001) begin
        pass_count++;
      end else begin
        $display("FAIL: sram_w16 addr %0d: expected %h, got %h", i, (i + 1) * 128'hDEAD_0001,
                 sram_q);
        fail_count++;
      end
    end

    $display("sram_w16: done");

    //-------------------------------------------------------
    // Test 2: sram_128b_w16 - write all, read back (async read)
    //-------------------------------------------------------
    $display("\n===== Test 2: sram_128b_w16 =====");

    // Write phase
    for (i = 0; i < 16; i++) begin
      @(negedge clk);
      sram128_cen = 0;
      sram128_wen = 0;  // write
      sram128_a   = i[3:0];
      sram128_d   = (i + 100) * 128'h0001_CAFE;
      @(posedge clk);
    end

    @(negedge clk);
    sram128_cen = 1;
    sram128_wen = 1;
    @(posedge clk);

    // Read phase (address registered, Q is combinational from add_q)
    for (i = 0; i < 16; i++) begin
      @(negedge clk);
      sram128_cen = 0;
      sram128_wen = 1;  // read
      sram128_a   = i[3:0];
      @(posedge clk);
      // add_q captured, Q updates combinationally
      #0.1;
      if (sram128_q == (i + 100) * 128'h0001_CAFE) begin
        pass_count++;
      end else begin
        $display("FAIL: sram_128b_w16 addr %0d: expected %h, got %h", i,
                 (i + 100) * 128'h0001_CAFE, sram128_q);
        fail_count++;
      end
    end

    $display("sram_128b_w16: done");

    //-------------------------------------------------------
    // Test 3: mac_16in - known dot product
    //-------------------------------------------------------
    $display("\n===== Test 3: mac_16in =====");

    // Test: all a[i]=1, all b[i]=1 => each product = 1 => sum = 16
    for (i = 0; i < PR; i++) begin
      mac_a[BW*(i+1)-1-:BW] = 8'sd1;
      mac_b[BW*(i+1)-1-:BW] = 8'sd1;
    end
    #1;
    if (mac_out == BW_PSUM'(16)) begin
      $display("PASS: mac_16in all-ones dot product = %0d", mac_out);
      pass_count++;
    end else begin
      $display("FAIL: mac_16in all-ones: expected 16, got %0d", $signed(mac_out));
      fail_count++;
    end

    // Test: a[i]=i+1, b[i]=1 => sum = 1+2+...+16 = 136
    for (i = 0; i < PR; i++) begin
      mac_a[BW*(i+1)-1-:BW] = (i + 1);
      mac_b[BW*(i+1)-1-:BW] = 8'sd1;
    end
    #1;
    if ($signed(mac_out) == 136) begin
      $display("PASS: mac_16in sequential dot product = %0d", $signed(mac_out));
      pass_count++;
    end else begin
      $display("FAIL: mac_16in sequential: expected 136, got %0d", $signed(mac_out));
      fail_count++;
    end

    // Test: negative values a[0]=-1, b[0]=1, rest 0 => out = -1
    mac_a = 0;
    mac_b = 0;
    mac_a[BW-1:0] = 8'hFF;  // -1 in 8-bit signed
    mac_b[BW-1:0] = 8'h01;  // +1
    #1;
    if ($signed(mac_out) == -1) begin
      $display("PASS: mac_16in negative = %0d", $signed(mac_out));
      pass_count++;
    end else begin
      $display("FAIL: mac_16in negative: expected -1, got %0d", $signed(mac_out));
      fail_count++;
    end

    //-------------------------------------------------------
    // Test 4: fifo_depth16 - write N values, read back in order
    //-------------------------------------------------------
    $display("\n===== Test 4: fifo_depth16 =====");

    // Release reset
    fifo_reset = 1;
    repeat (2) @(posedge clk);
    @(negedge clk);
    fifo_reset = 0;
    @(posedge clk);

    // Verify empty after reset
    if (fifo_empty == 1) begin
      $display("PASS: FIFO empty after reset");
      pass_count++;
    end else begin
      $display("FAIL: FIFO not empty after reset");
      fail_count++;
    end

    // Write 8 values
    for (i = 0; i < 8; i++) begin
      @(negedge clk);
      fifo_wr = 1;
      fifo_in = (i * 17 + 3) & 8'hFF;  // arbitrary pattern
      @(posedge clk);
    end
    @(negedge clk);
    fifo_wr = 0;
    @(posedge clk);

    // Verify not empty
    if (fifo_empty == 0) begin
      $display("PASS: FIFO not empty after writes");
      pass_count++;
    end else begin
      $display("FAIL: FIFO empty after writes");
      fail_count++;
    end

    // Read back 8 values and check FIFO order
    for (i = 0; i < 8; i++) begin
      @(negedge clk);
      fifo_rd = 1;
      // fifo_out is combinational from current rd_ptr
      if (fifo_out == ((i * 17 + 3) & 8'hFF)) begin
        pass_count++;
      end else begin
        $display("FAIL: FIFO read %0d: expected %0d, got %0d", i, (i * 17 + 3) & 8'hFF, fifo_out);
        fail_count++;
      end
      @(posedge clk);
    end
    @(negedge clk);
    fifo_rd = 0;
    @(posedge clk);

    //-------------------------------------------------------
    // Summary
    //-------------------------------------------------------
    $display("\n========================================");
    $display("  PASS: %0d  FAIL: %0d", pass_count, fail_count);
    if (fail_count == 0) $display("  ALL TESTS PASSED");
    else $display("  SOME TESTS FAILED");
    $display("========================================\n");

    $finish;
  end

endmodule

verilog/refactor_tb.vcd
$date
	Thu Mar 19 22:14:03 2026
$end
$version
	Icarus Verilog
$end
$timescale
	1ps
$end
$scope module refactor_tb $end
$var wire 128 ! sram_q [127:0] $end
$var wire 128 " sram128_q [127:0] $end
$var wire 20 # mac_out [19:0] $end
$var wire 8 $ fifo_out [7:0] $end
$var wire 1 % fifo_full $end
$var wire 1 & fifo_empty $end
$var parameter 32 ' BW $end
$var parameter 32 ( BW_PSUM $end
$var parameter 32 ) PR $end
$var parameter 32 * SRAM_BIT $end
$var reg 1 + clk $end
$var reg 8 , fifo_in [7:0] $end
$var reg 1 - fifo_rd $end
$var reg 1 . fifo_reset $end
$var reg 1 / fifo_wr $end
$var reg 128 0 mac_a [127:0] $end
$var reg 128 1 mac_b [127:0] $end
$var reg 4 2 sram128_a [3:0] $end
$var reg 1 3 sram128_cen $end
$var reg 128 4 sram128_d [127:0] $end
$var reg 1 5 sram128_wen $end
$var reg 4 6 sram_a [3:0] $end
$var reg 1 7 sram_cen $end
$var reg 128 8 sram_d [127:0] $end
$var reg 1 9 sram_wen $end
$var integer 32 : fail_count [31:0] $end
$var integer 32 ; i [31:0] $end
$var integer 32 < pass_count [31:0] $end
$scope module uut_fifo $end
$var wire 8 = in [7:0] $end
$var wire 1 - rd $end
$var wire 1 + rd_clk $end
$var wire 1 . reset $end
$var wire 1 / wr $end
$var wire 1 + wr_clk $end
$var wire 8 > out [7:0] $end
$var parameter 32 ? BW $end
$var parameter 32 @ SIMD $end
$var reg 1 A empty $end
$var reg 1 B full $end
$var reg 1 & o_empty $end
$var reg 1 % o_full $end
$var reg 5 C rd_ptr [4:0] $end
$var reg 5 D wr_ptr [4:0] $end
$scope module fifo_mux_16_1a $end
$var wire 4 E sel [3:0] $end
$var parameter 32 F BW $end
$var parameter 32 G SIMD $end
$var reg 8 H out [7:0] $end
$upscope $end
$upscope $end
$scope module uut_mac16 $end
$var wire 128 I a [127:0] $end
$var wire 128 J b [127:0] $end
$var parameter 32 K BW $end
$var parameter 32 L BW_PSUM $end
$var parameter 32 M PR $end
$var reg 20 N out [19:0] $end
$scope begin $ivl_for_loop0 $end
$var integer 32 O i [31:0] $end
$upscope $end
$scope begin $ivl_for_loop1 $end
$var integer 32 P i [31:0] $end
$upscope $end
$upscope $end
$scope module uut_sram $end
$var wire 4 Q A [3:0] $end
$var wire 1 7 CEN $end
$var wire 1 + CLK $end
$var wire 128 R D [127:0] $end
$var wire 1 9 WEN $end
$var parameter 32 S SRAM_BIT $end
$var reg 128 T Q [127:0] $end
$upscope $end
$scope module uut_sram128 $end
$var wire 4 U A [3:0] $end
$var wire 1 3 CEN $end
$var wire 1 + CLK $end
$var wire 128 V D [127:0] $end
$var wire 1 5 WEN $end
$var reg 128 W Q [127:0] $end
$var reg 4 X add_q [3:0] $end
$upscope $end
$upscope $end
$enddefinitions $end
$comment Show the parameter values. $end
$dumpall
b10000000 S
b10000 M
b10100 L
b1000 K
b1 G
b1000 F
b1 @
b1000 ?
b10000000 *
b10000 )
b10100 (
b1000 '
$end
#0
$dumpvars
bx X
bx W
b0 V
b0 U
bx T
b0 R
b0 Q
b10000 P
b10000 O
b0 N
b0 J
b0 I
bx H
b0 E
b0 D
b0 C
0B
1A
bx >
b0 =
b0 <
bx ;
b0 :
19
b0 8
17
b0 6
15
b0 4
13
b0 2
b0 1
b0 0
0/
1.
0-
b0 ,
0+
1&
0%
bx $
b0 #
bx "
bx !
$end
#500
1+
#1000
0+
#1500
1+
#2000
0+
#2500
b0 ;
1+
#3000
b11011110101011010000000000000001 8
b11011110101011010000000000000001 R
09
07
0+
#3500
b1 ;
1+
#4000
b110111101010110100000000000000010 8
b110111101010110100000000000000010 R
b1 6
b1 Q
0+
#4500
b10 ;
1+
#5000
b1010011100000001110000000000000011 8
b1010011100000001110000000000000011 R
b10 6
b10 Q
0+
#5500
b11 ;
1+
#6000
b1101111010101101000000000000000100 8
b1101111010101101000000000000000100 R
b11 6
b11 Q
0+
#6500
b100 ;
1+
#7000
b10001011001011000010000000000000101 8
b10001011001011000010000000000000101 R
b100 6
b100 Q
0+
#7500
b101 ;
1+
#8000
b10100111000000011100000000000000110 8
b10100111000000011100000000000000110 R
b101 6
b101 Q
0+
#8500
b110 ;
1+
#9000
b11000010110101110110000000000000111 8
b11000010110101110110000000000000111 R
b110 6
b110 Q
0+
#9500
b111 ;
1+
#10000
b11011110101011010000000000000001000 8
b11011110101011010000000000000001000 R
b111 6
b111 Q
0+
#10500
b1000 ;
1+
#11000
b11111010100000101010000000000001001 8
b11111010100000101010000000000001001 R
b1000 6
b1000 Q
0+
#11500
b1001 ;
1+
#12000
b100010110010110000100000000000001010 8
b100010110010110000100000000000001010 R
b1001 6
b1001 Q
0+
#12500
b1010 ;
1+
#13000
b100110010001011011110000000000001011 8
b100110010001011011110000000000001011 R
b1010 6
b1010 Q
0+
#13500
b1011 ;
1+
#14000
b101001110000000111000000000000001100 8
b101001110000000111000000000000001100 R
b1011 6
b1011 Q
0+
#14500
b1100 ;
1+
#15000
b101101001110110010010000000000001101 8
b101101001110110010010000000000001101 R
b1100 6
b1100 Q
0+
#15500
b1101 ;
1+
#16000
b110000101101011101100000000000001110 8
b110000101101011101100000000000001110 R
b1101 6
b1101 Q
0+
#16500
b1110 ;
1+
#17000
b110100001100001000110000000000001111 8
b110100001100001000110000000000001111 R
b1110 6
b1110 Q
0+
#17500
b1111 ;
1+
#18000
b110111101010110100000000000000010000 8
b110111101010110100000000000000010000 R
b1111 6
b1111 Q
0+
#18500
b10000 ;
1+
#19000
19
17
0+
#19500
b0 ;
1+
#20000
b0 6
b0 Q
07
0+
#20500
b11011110101011010000000000000001 !
b11011110101011010000000000000001 T
1+
#21000
17
0+
#21500
b1 ;
b1 <
1+
#22000
b1 6
b1 Q
07
0+
#22500
b110111101010110100000000000000010 !
b110111101010110100000000000000010 T
1+
#23000
17
0+
#23500
b10 ;
b10 <
1+
#24000
b10 6
b10 Q
07
0+
#24500
b1010011100000001110000000000000011 !
b1010011100000001110000000000000011 T
1+
#25000
17
0+
#25500
b11 ;
b11 <
1+
#26000
b11 6
b11 Q
07
0+
#26500
b1101111010101101000000000000000100 !
b1101111010101101000000000000000100 T
1+
#27000
17
0+
#27500
b100 ;
b100 <
1+
#28000
b100 6
b100 Q
07
0+
#28500
b10001011001011000010000000000000101 !
b10001011001011000010000000000000101 T
1+
#29000
17
0+
#29500
b101 ;
b101 <
1+
#30000
b101 6
b101 Q
07
0+
#30500
b10100111000000011100000000000000110 !
b10100111000000011100000000000000110 T
1+
#31000
17
0+
#31500
b110 ;
b110 <
1+
#32000
b110 6
b110 Q
07
0+
#32500
b11000010110101110110000000000000111 !
b11000010110101110110000000000000111 T
1+
#33000
17
0+
#33500
b111 ;
b111 <
1+
#34000
b111 6
b111 Q
07
0+
#34500
b11011110101011010000000000000001000 !
b11011110101011010000000000000001000 T
1+
#35000
17
0+
#35500
b1000 ;
b1000 <
1+
#36000
b1000 6
b1000 Q
07
0+
#36500
b11111010100000101010000000000001001 !
b11111010100000101010000000000001001 T
1+
#37000
17
0+
#37500
b1001 ;
b1001 <
1+
#38000
b1001 6
b1001 Q
07
0+
#38500
b100010110010110000100000000000001010 !
b100010110010110000100000000000001010 T
1+
#39000
17
0+
#39500
b1010 ;
b1010 <
1+
#40000
b1010 6
b1010 Q
07
0+
#40500
b100110010001011011110000000000001011 !
b100110010001011011110000000000001011 T
1+
#41000
17
0+
#41500
b1011 ;
b1011 <
1+
#42000
b1011 6
b1011 Q
07
0+
#42500
b101001110000000111000000000000001100 !
b101001110000000111000000000000001100 T
1+
#43000
17
0+
#43500
b1100 ;
b1100 <
1+
#44000
b1100 6
b1100 Q
07
0+
#44500
b101101001110110010010000000000001101 !
b101101001110110010010000000000001101 T
1+
#45000
17
0+
#45500
b1101 ;
b1101 <
1+
#46000
b1101 6
b1101 Q
07
0+
#46500
b110000101101011101100000000000001110 !
b110000101101011101100000000000001110 T
1+
#47000
17
0+
#47500
b1110 ;
b1110 <
1+
#48000
b1110 6
b1110 Q
07
0+
#48500
b110100001100001000110000000000001111 !
b110100001100001000110000000000001111 T
1+
#49000
17
0+
#49500
b1111 ;
b1111 <
1+
#50000
b1111 6
b1111 Q
07
0+
#50500
b110111101010110100000000000000010000 !
b110111101010110100000000000000010000 T
1+
#51000
17
0+
#51500
b0 ;
b10000 <
1+
#52000
b101100110100101100111000 4
b101100110100101100111000 V
05
03
0+
#52500
b1 ;
1+
#53000
b101101010001011000110110 4
b101101010001011000110110 V
b1 2
b1 U
0+
#53500
b10 ;
1+
#54000
b101101101110000100110100 4
b101101101110000100110100 V
b10 2
b10 U
0+
#54500
b11 ;
1+
#55000
b101110001010110000110010 4
b101110001010110000110010 V
b11 2
b11 U
0+
#55500
b100 ;
1+
#56000
b101110100111011100110000 4
b101110100111011100110000 V
b100 2
b100 U
0+
#56500
b101 ;
1+
#57000
b101111000100001000101110 4
b101111000100001000101110 V
b101 2
b101 U
0+
#57500
b110 ;
1+
#58000
b101111100000110100101100 4
b101111100000110100101100 V
b110 2
b110 U
0+
#58500
b111 ;
1+
#59000
b101111111101100000101010 4
b101111111101100000101010 V
b111 2
b111 U
0+
#59500
b1000 ;
1+
#60000
b110000011010001100101000 4
b110000011010001100101000 V
b1000 2
b1000 U
0+
#60500
b1001 ;
1+
#61000
b110000110110111000100110 4
b110000110110111000100110 V
b1001 2
b1001 U
0+
#61500
b1010 ;
1+
#62000
b110001010011100100100100 4
b110001010011100100100100 V
b1010 2
b1010 U
0+
#62500
b1011 ;
1+
#63000
b110001110000010000100010 4
b110001110000010000100010 V
b1011 2
b1011 U
0+
#63500
b1100 ;
1+
#64000
b110010001100111100100000 4
b110010001100111100100000 V
b1100 2
b1100 U
0+
#64500
b1101 ;
1+
#65000
b110010101001101000011110 4
b110010101001101000011110 V
b1101 2
b1101 U
0+
#65500
b1110 ;
1+
#66000
b110011000110010100011100 4
b110011000110010100011100 V
b1110 2
b1110 U
0+
#66500
b1111 ;
1+
#67000
b110011100011000000011010 4
b110011100011000000011010 V
b1111 2
b1111 U
0+
#67500
b10000 ;
1+
#68000
15
13
0+
#68500
b0 ;
1+
#69000
b0 2
b0 U
03
0+
#69500
b101100110100101100111000 "
b101100110100101100111000 W
b0 X
1+
#69600
b1 ;
b10001 <
#70000
b1 2
b1 U
0+
#70500
b101101010001011000110110 "
b101101010001011000110110 W
b1 X
1+
#70600
b10 ;
b10010 <
#71000
b10 2
b10 U
0+
#71500
b101101101110000100110100 "
b101101101110000100110100 W
b10 X
1+
#71600
b11 ;
b10011 <
#72000
b11 2
b11 U
0+
#72500
b101110001010110000110010 "
b101110001010110000110010 W
b11 X
1+
#72600
b100 ;
b10100 <
#73000
b100 2
b100 U
0+
#73500
b101110100111011100110000 "
b101110100111011100110000 W
b100 X
1+
#73600
b101 ;
b10101 <
#74000
b101 2
b101 U
0+
#74500
b101111000100001000101110 "
b101111000100001000101110 W
b101 X
1+
#74600
b110 ;
b10110 <
#75000
b110 2
b110 U
0+
#75500
b101111100000110100101100 "
b101111100000110100101100 W
b110 X
1+
#75600
b111 ;
b10111 <
#76000
b111 2
b111 U
0+
#76500
b101111111101100000101010 "
b101111111101100000101010 W
b111 X
1+
#76600
b1000 ;
b11000 <
#77000
b1000 2
b1000 U
0+
#77500
b110000011010001100101000 "
b110000011010001100101000 W
b1000 X
1+
#77600
b1001 ;
b11001 <
#78000
b1001 2
b1001 U
0+
#78500
b110000110110111000100110 "
b110000110110111000100110 W
b1001 X
1+
#78600
b1010 ;
b11010 <
#79000
b1010 2
b1010 U
0+
#79500
b110001010011100100100100 "
b110001010011100100100100 W
b1010 X
1+
#79600
b1011 ;
b11011 <
#80000
b1011 2
b1011 U
0+
#80500
b110001110000010000100010 "
b110001110000010000100010 W
b1011 X
1+
#80600
b1100 ;
b11100 <
#81000
b1100 2
b1100 U
0+
#81500
b110010001100111100100000 "
b110010001100111100100000 W
b1100 X
1+
#81600
b1101 ;
b11101 <
#82000
b1101 2
b1101 U
0+
#82500
b110010101001101000011110 "
b110010101001101000011110 W
b1101 X
1+
#82600
b1110 ;
b11110 <
#83000
b1110 2
b1110 U
0+
#83500
b110011000110010100011100 "
b110011000110010100011100 W
b1110 X
1+
#83600
b1111 ;
b11111 <
#84000
b1111 2
b1111 U
0+
#84500
b110011100011000000011010 "
b110011100011000000011010 W
b1111 X
1+
#84600
b10000 #
b10000 N
b10000 P
b10000 O
b1000000010000000100000001000000010000000100000001000000010000000100000001000000010000000100000001000000010000000100000001 1
b1000000010000000100000001000000010000000100000001000000010000000100000001000000010000000100000001000000010000000100000001 J
b1000000010000000100000001000000010000000100000001000000010000000100000001000000010000000100000001000000010000000100000001 0
b1000000010000000100000001000000010000000100000001000000010000000100000001000000010000000100000001000000010000000100000001 I
b10000 ;
b100000 <
#85000
0+
#85500
1+
#85600
b10000 P
b10001000 #
b10001000 N
b10000 O
b10000000011110000111000001101000011000000101100001010000010010000100000000111000001100000010100000100000000110000001000000001 0
b10000000011110000111000001101000011000000101100001010000010010000100000000111000001100000010100000100000000110000001000000001 I
b10000 ;
b100001 <
#86000
0+
#86500
1+
#86600
b10000 P
b11111111111111111111 #
b11111111111111111111 N
b10000 O
b1 1
b1 J
b11111111 0
b11111111 I
b100010 <
#87000
0+
#87500
1+
#87600
b100011 <
#88000
0+
#88500
1+
#89000
0+
#89500
1+
#90000
0.
0+
#90500
b0 ;
b100100 <
1+
#91000
b11 ,
b11 =
1/
0+
#91500
b11 $
b11 >
b11 H
0&
0A
b1 D
b1 ;
1+
#92000
b10100 ,
b10100 =
0+
#92500
b10 D
b10 ;
1+
#93000
b100101 ,
b100101 =
0+
#93500
b11 D
b11 ;
1+
#94000
b110110 ,
b110110 =
0+
#94500
b100 D
b100 ;
1+
#95000
b1000111 ,
b1000111 =
0+
#95500
b101 D
b101 ;
1+
#96000
b1011000 ,
b1011000 =
0+
#96500
b110 D
b110 ;
1+
#97000
b1101001 ,
b1101001 =
0+
#97500
b111 D
b111 ;
1+
#98000
b1111010 ,
b1111010 =
0+
#98500
b1000 D
b1000 ;
1+
#99000
0/
0+
#99500
b0 ;
b100101 <
1+
#100000
b100110 <
1-
0+
#100500
b10100 $
b10100 >
b10100 H
b1 E
b1 C
b1 ;
1+
#101000
b100111 <
0+
#101500
b100101 $
b100101 >
b100101 H
b10 E
b10 C
b10 ;
1+
#102000
b101000 <
0+
#102500
b110110 $
b110110 >
b110110 H
b11 E
b11 C
b11 ;
1+
#103000
b101001 <
0+
#103500
b1000111 $
b1000111 >
b1000111 H
b100 E
b100 C
b100 ;
1+
#104000
b101010 <
0+
#104500
b1011000 $
b1011000 >
b1011000 H
b101 E
b101 C
b101 ;
1+
#105000
b101011 <
0+
#105500
b1101001 $
b1101001 >
b1101001 H
b110 E
b110 C
b110 ;
1+
#106000
b101100 <
0+
#106500
b1111010 $
b1111010 >
b1111010 H
b111 E
b111 C
b111 ;
1+
#107000
b101101 <
0+
#107500
bx $
bx >
bx H
1&
1A
b1000 E
b1000 C
b1000 ;
1+
#108000
0-
0+
